margsoft/__init__.py
margsoft/mineral.py
margsoft-0.0.28.dist-info/LICENSE
margsoft-0.0.28.dist-info/METADATA
margsoft-0.0.28.dist-info/WHEEL
margsoft-0.0.28.dist-info/top_level.txt
margsoft-0.0.28.dist-info/RECORD
