Metadata-Version: 2.1
Name: margsoft
Version: 0.0.28
Summary: data collection package
Home-page: https://github.com/Codebugged-Research/datacollection
Author: Codebugged-Research
Author-email: thecodebugged@gmail.com
License: MIT
Classifier: Intended Audience :: Developers
Classifier: Operating System :: OS Independent
Classifier: Natural Language :: Chinese (Simplified)
Classifier: Programming Language :: Python :: 3.6
Classifier: Topic :: Utilities
Classifier: Programming Language :: Python :: 3.7
Classifier: Topic :: Utilities
Classifier: Programming Language :: Python :: 3.8
Classifier: Topic :: Utilities
Requires-Python: >=3.6
License-File: LICENSE
Requires-Dist: opencv-python
Requires-Dist: numpy
Requires-Dist: ultralytics
